setup.cfg
setup.py
serial_deserial_lib/__init__.py
serial_deserial_lib/ser_deser_class.py
serial_deserial_lib/ser_deser_class_test.py
serial_deserial_lib.egg-info/PKG-INFO
serial_deserial_lib.egg-info/SOURCES.txt
serial_deserial_lib.egg-info/dependency_links.txt
serial_deserial_lib.egg-info/not-zip-safe
serial_deserial_lib.egg-info/top_level.txt