Metadata-Version: 2.1
Name: serial-deserial-lib
Version: 0.1
Summary: Serialisation and deserialoisation class
Author-email: zhagorov2004@gmail.com
